nidaba/__init__.py
nidaba/api.py
nidaba/celery.py
nidaba/cli.py
nidaba/config.py
nidaba/image.py
nidaba/lex.py
nidaba/lock.py
nidaba/merge_hocr.py
nidaba/nidaba.py
nidaba/nidabaexceptions.py
nidaba/storage.py
nidaba/tei.py
nidaba/uzn.py
nidaba/web.py
nidaba/algorithms/__init__.py
nidaba/algorithms/otsu.py
nidaba/algorithms/string.py
nidaba/contrib/__init__.py
nidaba/contrib/mkdict.py
nidaba/plugins/__init__.py
nidaba/plugins/kraken.py
nidaba/plugins/leptonica.py
nidaba/plugins/ocropus.py
nidaba/plugins/pybossa.py
nidaba/plugins/tesseract.py
nidaba/static/bootstrap/css/bootstrap-glyphicons.css
nidaba/static/bootstrap/css/bootstrap-theme.css
nidaba/static/bootstrap/css/bootstrap-theme.min.css
nidaba/static/bootstrap/css/bootstrap.css
nidaba/static/bootstrap/css/bootstrap.min.css
nidaba/static/bootstrap/fonts/glyphicons-halflings-regular.eot
nidaba/static/bootstrap/fonts/glyphicons-halflings-regular.svg
nidaba/static/bootstrap/fonts/glyphicons-halflings-regular.ttf
nidaba/static/bootstrap/fonts/glyphicons-halflings-regular.woff
nidaba/static/bootstrap/js/bootstrap.js
nidaba/static/bootstrap/js/bootstrap.min.js
nidaba/static/css/basic.min.css
nidaba/static/css/bootstrap-multiselect.css
nidaba/static/css/style.css
nidaba/static/css/style.css.map
nidaba/static/css/style.scss
nidaba/static/css/.sass-cache/a5b8e9f858c72886a7453f9d335734eaa6468476/style.scssc
nidaba/static/images/opp-logo.png
nidaba/static/images/step-process.png
nidaba/static/images/step-results.png
nidaba/static/images/step-scan.png
nidaba/static/images/tutorial-dpi-preview1.png
nidaba/static/images/tutorial-dpi-preview2.png
nidaba/static/images/tutorial-font-griechische-antiquagreek.png
nidaba/static/images/tutorial-font-porsongreek.png
nidaba/static/images/tutorial-font-zephgreek.png
nidaba/static/images/tutorial-scan-settings.png
nidaba/static/js/backbone-min.js
nidaba/static/js/bootstrap-multiselect-collapsible-groups.js
nidaba_client-2.0.1.dist-info/DESCRIPTION.rst
nidaba_client-2.0.1.dist-info/METADATA
nidaba_client-2.0.1.dist-info/RECORD
nidaba_client-2.0.1.dist-info/WHEEL
nidaba_client-2.0.1.dist-info/entry_points.txt
nidaba_client-2.0.1.dist-info/metadata.json
nidaba_client-2.0.1.dist-info/pbr.json
nidaba_client-2.0.1.dist-info/top_level.txt
