Metadata-Version: 2.0
Name: nidaba-client
Version: 2.0.1
Summary: Expandable and scalable OCR pipeline client
Home-page: UNKNOWN
Author: Open Greek and Latin
Author-email: kiessling@dh.uni-leipzig.de
License: GPLv2+
Keywords: ocr
Requires-Dist: click (>=4.0)
Requires-Dist: requests-toolbelt
